{
  "name": "CreatureSimulator",
  "tree": {
    "$className": "DataModel",
    "ReplicatedStorage": {
      "$className": "ReplicatedStorage",
      "Modules": {
        "$className": "Folder",
        "GameConfig": { "$path": "src/ReplicatedStorage/Modules/GameConfig.lua" },
        "PetSystem": { "$path": "src/ReplicatedStorage/Modules/PetSystem.lua" }
      }
    },
    "ServerScriptService": {
      "$className": "ServerScriptService",
      "GameManager": { "$path": "src/ServerScriptService/Server/GameManager.server.lua" },
      "HatchHandler": { "$path": "src/ServerScriptService/Server/HatchHandler.server.lua" }
    },
    "StarterPlayer": {
      "$className": "StarterPlayer",
      "StarterPlayerScripts": {
        "$className": "StarterPlayerScripts",
        "UI": { "$path": "src/StarterPlayer/StarterPlayerScripts/Client/UI.client.lua" },
        "HatchUI": { "$path": "src/StarterPlayer/StarterPlayerScripts/Client/HatchUI.client.lua" },
        "SimplePetsButton": { "$path": "src/StarterPlayer/StarterPlayerScripts/Client/SimplePetsButton.client.lua" }
      }
    },
    "Workspace": {
      "$className": "Workspace",
      "SpawnLocation": { "$className": "SpawnLocation", "$properties": { "Position": [0, 10, 0] } }
    }
  }
}